bias_lens/__init__.py
bias_lens/bias_model_explainer_factory.py
bias_lens/bias_ner_classifier.py
bias_lens/explainers/__init__.py
bias_lens/explainers/attention_explainer.py
bias_lens/explainers/base_explainer.py
bias_lens/explainers/cf_explainer.py
bias_lens/explainers/deeplift_explainer.py
bias_lens/explainers/ig_explainer.py
bias_lens/explainers/lime_explainer.py
bias_lens/explainers/lrp_explainer.py
bias_lens/explainers/occlusion_explainer.py
bias_lens/explainers/probability_explainer_mixin.py
bias_lens/explainers/shap_explainer.py
bias_lens-0.1.1.dist-info/LICENSE
bias_lens-0.1.1.dist-info/METADATA
bias_lens-0.1.1.dist-info/WHEEL
bias_lens-0.1.1.dist-info/RECORD
