Metadata-Version: 2.3
Name: bias-lens
Version: 0.1.1
Summary: A library for bias detection and explainable AI methods in NLP models.
License: MIT
Keywords: bias,explainable-ai,XAI,NLP,transformers,fairness
Author: bhavaniit24
Author-email: loganthan.20201212@iit.ac.lk
Requires-Python: >=3.12,<4.0
Classifier: License :: OSI Approved :: MIT License
Classifier: Programming Language :: Python :: 3
Classifier: Programming Language :: Python :: 3.12
Classifier: Programming Language :: Python :: 3.13
Requires-Dist: captum (>=0.7.0,<0.8.0)
Requires-Dist: lime (>=0.2.0.1,<0.3.0.0)
Requires-Dist: llvmlite (>=0.44.0,<0.45.0)
Requires-Dist: matplotlib (>=3.10.0,<4.0.0)
Requires-Dist: numba (>=0.61.0,<0.62.0)
Requires-Dist: shap (>=0.46.0,<0.47.0)
Requires-Dist: torch (>=2.6.0,<3.0.0)
Project-URL: Homepage, https://github.com/yourusername/bias-lens
Project-URL: Repository, https://github.com/yourusername/bias-lens
